backend/__init__.py
backend/blif/__init__.py
backend/blif/blifReader.py
backend/blif/blifWriter.py
backend/blif/rewriteBlif.py
backend/blif/network/__init__.py
backend/blif/network/blif.py
backend/blif/network/blifGraph.py
backend/cute/__init__.py
backend/cute/cleanupDangling.py
backend/cute/cutExpansion.py
backend/cute/cutless.py
backend/cute/printCuts.py
backend/cute/timingLabel.py
backend/map/__init__.py
backend/map/dt.py
backend/map/map.py
backend/map/simulate.py
backend/map/tt.py
backend/milp/__init__.py
backend/milp/basicModel.py
backend/milp/graphModel.py
backend/milp/mapbufModel.py
backend/milp/timingModel.py
leap_backend-0.1.0.dist-info/LICENSE
leap_backend-0.1.0.dist-info/METADATA
leap_backend-0.1.0.dist-info/WHEEL
leap_backend-0.1.0.dist-info/top_level.txt
leap_backend-0.1.0.dist-info/RECORD
