Metadata-Version: 2.1
Name: leap-backend
Version: 0.1.0
Summary: The backend of the LEAP framework
Author: Hanyu Wang
License: MIT License
Project-URL: Repository, https://github.com/Nozidoali/leap-backend
Keywords: high-level synthesis,verilog,system verilog
Classifier: Programming Language :: Python :: 3
Classifier: Operating System :: OS Independent
Requires-Python: >=3.11
License-File: LICENSE
Requires-Dist: gurobipy>=11.0
Requires-Dist: pygraphviz>=1.10
